argparse_h.py
argparse_history-0.2.5.dist-info/LICENSE
argparse_history-0.2.5.dist-info/METADATA
argparse_history-0.2.5.dist-info/WHEEL
argparse_history-0.2.5.dist-info/top_level.txt
argparse_history-0.2.5.dist-info/RECORD
