Metadata-Version: 2.1
Name: argparse-history
Version: 0.2.5
Summary: An extension of argparse with history tracking
Home-page: https://github.com/dimitrix-cnrs/argparse-history
Author: Dimitry Khvorostyanov
Author-email: dimitry.khvorostyanov@locean.ipsl.fr
Keywords: argparse history command-line
Classifier: Programming Language :: Python :: 3
Classifier: License :: OSI Approved :: MIT License
Classifier: Operating System :: OS Independent
Requires-Python: >=3.8
License-File: LICENSE
